Workbook

Sheet 使用说明
A1: 个人资金管理模板｜浮动工资 + 不定期收入版
A3: 使用流程 | B3: 说明
A4: 1. 先改参数 | B4: 在《参数设置》里修改黄色单元格：工资收入下限/上限、保守预算基准、比例、应急金目标。
A5: 2. 记录流水 | B5: 在《流水记录》逐笔记录收入和支出。工资收入的“子类别”填“工资”；非工资收入填“奖金/绩效、副业收入、理财收益、红包/礼金、报销、其他收入”等。
A6: 3. 保守预算 | B6: 系统默认按 7000 元保守工资基准做基础预算，避免低收入月份超支。
A7: 4. 处理额外收入 | B7: 实际总收入超过保守预算基准的部分，会自动按 70% 储蓄/投资/还债、20% 专项准备金、10% 弹性消费分配。
A8: 5. 看仪表盘 | B8: 《月度仪表盘》会自动显示本月工资收入、非工资收入、额外收入、结余、储蓄/偿债率、应急金和净资产。
A9: 6. 月底复盘 | B9: 月底看《收入规划》和《月度预算》：低收入月控制弹性消费；高收入月优先补应急金、还高息债或定投。
A10: 颜色说明 | B10: 黄色为可手动修改；蓝色为自动计算公式，通常不要手动改。

Sheet 参数设置
A1: 参数设置｜按你的浮动收入情况设置
A3: 项目 | B3: 数值 | C3: 说明 | D3: 账户 | E3: 类型 | F3: 子类别 | G3: 状态 | H3: 风险等级
A4: 工资收入下限 | B4: 7000 | C4: 你的月工资大致最低值；用于提醒工资异常低的月份。 | D4: 工资卡 | E4: 收入 | F4: 工资 | G4: 待录入 | H4: 保守
A5: 工资收入上限 | B5: 8500 | C5: 你的月工资大致最高值；用于识别高收入月份。 | D5: 生活账户 | E5: 必要支出 | F5: 奖金/绩效 | G5: 正常 | H5: 平衡
A6: 保守预算基准 | B6: 7000 | C6: 建议用工资下限做预算，不依赖奖金、副业或临时收入。 | D6: 应急金账户 | E6: 储蓄投资 | F6: 副业收入 | G6: 优秀 | H6: 进取
A7: 工资收入参考均值 | B7: =(B4+B5)/2 -> 7750 | C7: 仅供参考，用来观察长期平均收入。 | D7: 投资账户 | E7: 弹性消费 | F7: 理财收益 | G7: 超支
A8: 必要支出比例 | B8: 0.5 | C8: 以保守预算基准计算。 | D8: 快乐消费账户 | E8: 债务还款 | F8: 红包/礼金 | G8: 需要关注
A9: 基础储蓄/投资/还债比例 | B9: 0.3 | C9: 以保守预算基准计算。 | D9: 债务还款账户 | E9: 专项准备金 | F9: 报销 | G9: 进行中
A10: 基础弹性消费比例 | B10: 0.2 | C10: 以保守预算基准计算。 | D10: 专项准备金账户 | E10: 转账 | F10: 其他收入 | G10: 已完成
A11: 应急金目标月数 | B11: 3 | C11: 建议先做到 3 个月必要生活费，再逐步提高。 | D11: 其他 | F11: 房租/房贷
A12: 每月必要生活费估算 | B12: 4000 | C12: 用于计算应急金目标；请按你的真实最低生活费修改。 | F12: 餐饮
A13: 年度 | B13: 2026 | C13: 用于生成月度表。 | F13: 交通
A14: 额外收入→储蓄/投资/还债 | B14: 0.7 | C14: 总收入超过保守预算基准的部分。 | F14: 水电通讯
A15: 额外收入→专项准备金 | B15: 0.2 | C15: 用于年度账单、旅行、学习、维修、红包等不规则支出。 | F15: 医疗
A16: 额外收入→弹性消费 | B16: 0.1 | C16: 给自己留一点奖励，但避免额外收入全部花掉。 | F16: 应急金
A17: 债务偿还策略 | B17: 先还最高年利率 | C17: 适合多数高息消费贷/信用卡债务。 | F17: 基金定投
A18: 复盘提醒 | B18: 每月底复盘一次 | C18: 固定时间复盘，减少临时决策。 | F18: 股票/权益
A19: 基础比例合计 | B19: =SUM(B8:B10) -> 1 | C19: 应等于 100%。 | F19: 债券/固收
A20: 额外收入比例合计 | B20: =SUM(B14:B16) -> 1 | C20: 应等于 100%。 | F20: 信用卡/消费贷
A21: 校验结果 | B21: =IF(AND(ABS(B19-1)<0.0001,ABS(B20-1)<0.0001,B4<=B5),"通过","请检查比例或工资区间") -> 通过 | C21: 若非“通过”，请检查黄色参数。 | F21: 专项准备金
A22: 建议 | B22: 工资按下限预算；高于下限和非工资收入优先补安全垫/还债/投资 | F22: 娱乐
F23: 购物
F24: 旅行
F25: 学习提升
F26: 其他

Sheet 流水记录
A1: 流水记录｜逐笔记录收入、支出、储蓄、还债
A3: 日期 | B3: 月份 | C3: 账户 | D3: 类型 | E3: 子类别 | F3: 收入来源/资金去向 | G3: 是否固定 | H3: 说明 | I3: 金额 | J3: 备注
A4: 46023 | B4: =IF(A4="","",DATE(YEAR(A4),MONTH(A4),1)) -> 46023 | C4: 工资卡 | D4: 收入 | E4: 工资 | F4: 公司工资 | G4: 浮动 | H4: 工资到账 | I4: 7800 | J4: 示例：工资在 7000-8500 间浮动
A5: 46032 | B5: =IF(A5="","",DATE(YEAR(A5),MONTH(A5),1)) -> 46023 | C5: 工资卡 | D5: 收入 | E5: 副业收入 | F5: 副业/兼职 | G5: 一次性 | H5: 副业收入 | I5: 800 | J5: 示例：非工资收入
A6: 46047 | B6: =IF(A6="","",DATE(YEAR(A6),MONTH(A6),1)) -> 46023 | C6: 工资卡 | D6: 收入 | E6: 奖金/绩效 | F6: 绩效奖金 | G6: 一次性 | H6: 奖金到账 | I6: 500 | J6: 示例：不定期收入
A7: 46024 | B7: =IF(A7="","",DATE(YEAR(A7),MONTH(A7),1)) -> 46023 | C7: 生活账户 | D7: 必要支出 | E7: 房租/房贷 | F7: 房东/房贷 | G7: 固定 | H7: 房租 | I7: 2500 | J7: 示例
A8: 46028 | B8: =IF(A8="","",DATE(YEAR(A8),MONTH(A8),1)) -> 46023 | C8: 生活账户 | D8: 必要支出 | E8: 餐饮 | F8: 日常餐饮 | G8: 浮动 | H8: 餐饮 | I8: 900 | J8: 示例
A9: 46030 | B9: =IF(A9="","",DATE(YEAR(A9),MONTH(A9),1)) -> 46023 | C9: 生活账户 | D9: 必要支出 | E9: 交通 | F9: 通勤 | G9: 浮动 | H9: 交通 | I9: 250 | J9: 示例
A10: 46031 | B10: =IF(A10="","",DATE(YEAR(A10),MONTH(A10),1)) -> 46023 | C10: 生活账户 | D10: 必要支出 | E10: 水电通讯 | F10: 水电网话费 | G10: 固定 | H10: 水电通讯 | I10: 250 | J10: 示例
A11: 46034 | B11: =IF(A11="","",DATE(YEAR(A11),MONTH(A11),1)) -> 46023 | C11: 应急金账户 | D11: 储蓄投资 | E11: 应急金 | F11: 安全垫 | G11: 固定 | H11: 应急金转入 | I11: 1200 | J11: 示例
A12: 46035 | B12: =IF(A12="","",DATE(YEAR(A12),MONTH(A12),1)) -> 46023 | C12: 投资账户 | D12: 储蓄投资 | E12: 基金定投 | F12: 指数基金 | G12: 固定 | H12: 基金定投 | I12: 1500 | J12: 示例
A13: 46040 | B13: =IF(A13="","",DATE(YEAR(A13),MONTH(A13),1)) -> 46023 | C13: 债务还款账户 | D13: 债务还款 | E13: 信用卡/消费贷 | F13: 信用卡/消费贷 | G13: 固定 | H13: 还款 | I13: 900 | J13: 示例
A14: 46042 | B14: =IF(A14="","",DATE(YEAR(A14),MONTH(A14),1)) -> 46023 | C14: 专项准备金账户 | D14: 专项准备金 | E14: 专项准备金 | F14: 年度/临时支出 | G14: 固定 | H14: 准备金转入 | I14: 400 | J14: 示例
A15: 46044 | B15: =IF(A15="","",DATE(YEAR(A15),MONTH(A15),1)) -> 46023 | C15: 快乐消费账户 | D15: 弹性消费 | E15: 娱乐 | F15: 聚餐娱乐 | G15: 浮动 | H15: 聚餐 | I15: 600 | J15: 示例
A16: 46048 | B16: =IF(A16="","",DATE(YEAR(A16),MONTH(A16),1)) -> 46023 | C16: 快乐消费账户 | D16: 弹性消费 | E16: 购物 | F16: 日用品/服饰 | G16: 浮动 | H16: 购物 | I16: 400 | J16: 示例
B17: =IF(A17="","",DATE(YEAR(A17),MONTH(A17),1))
B18: =IF(A18="","",DATE(YEAR(A18),MONTH(A18),1))
B19: =IF(A19="","",DATE(YEAR(A19),MONTH(A19),1))
B20: =IF(A20="","",DATE(YEAR(A20),MONTH(A20),1))
B21: =IF(A21="","",DATE(YEAR(A21),MONTH(A21),1))
B22: =IF(A22="","",DATE(YEAR(A22),MONTH(A22),1))
B23: =IF(A23="","",DATE(YEAR(A23),MONTH(A23),1))
B24: =IF(A24="","",DATE(YEAR(A24),MONTH(A24),1))
B25: =IF(A25="","",DATE(YEAR(A25),MONTH(A25),1))
B26: =IF(A26="","",DATE(YEAR(A26),MONTH(A26),1))
B27: =IF(A27="","",DATE(YEAR(A27),MONTH(A27),1))
B28: =IF(A28="","",DATE(YEAR(A28),MONTH(A28),1))
... B503: =IF(A503="","",DATE(YEAR(A503),MONTH(A503),1))

Sheet 收入规划
A1: 收入规划｜工资浮动区间与不定期收入跟踪
A3: 指标 | B3: 数值 | C3: 说明 | E3: 额外收入使用规则
A4: 工资下限 | B4: =参数设置!$B$4 -> 7000 | C4: 低于此值会在月表提醒。 | E4: 1. 工资预算先按保守基准，不按最高工资花钱。
A5: 工资上限 | B5: =参数设置!$B$5 -> 8500 | C5: 高于此值说明工资明显较高。 | E5: 2. 工资高于保守基准的部分 + 非工资收入 = 额外收入。
A6: 保守预算基准 | B6: =参数设置!$B$6 -> 7000 | C6: 预算不按高收入月份膨胀。 | E6: 3. 额外收入默认：70% 储蓄/投资/还债，20% 专项准备金，10% 弹性消费。
A7: 工资参考均值 | B7: =参数设置!$B$7 -> 7750 | C7: 仅供观察。 | E7: 4. 当应急金未满时，建议把额外收入中的储蓄部分优先补应急金。
A8: 已录入月份数 | B8: =COUNTIF(月度预算!$D$6:$D$17,">0") -> 1 | C8: 只统计已记录收入的月份。
A9: 已录入总收入 | B9: =SUM(月度预算!$D$6:$D$17) -> 9100
A10: 已录入非工资收入 | B10: =SUM(月度预算!$C$6:$C$17) -> 1300
A11: 平均月总收入 | B11: =IFERROR(B9/B8,0) -> 9100
A14: 月份 | B14: 工资收入 | C14: 非工资收入 | D14: 总收入 | E14: 额外收入 | F14: 工资区间提醒 | G14: 建议储蓄/还债 | H14: 建议准备金 | I14: 建议弹性 | J14: 本月结余 | K14: 备注
A15: =月度预算!A6 -> 46023 | B15: 0 | C15: 0 | D15: 0 | E15: 0 | F15: =IF(D15=0,"待录入",IF(B15<参数设置!$B$4,"工资低于下限",IF(B15>参数设置!$B$5,"工资高于上限","工资在区间内"))) -> 待录入 | G15: =月度预算!M6 -> 3570 | H15: =月度预算!N6 -> 420 | I15: =月度预算!O6 -> 1610 | J15: =月度预算!U6 -> 200
A16: =月度预算!A7 -> 46054 | B16: =月度预算!B7 -> 0 | C16: =月度预算!C7 -> 0 | D16: =月度预算!D7 -> 0 | E16: =月度预算!I7 -> 0 | F16: =IF(D16=0,"待录入",IF(B16<参数设置!$B$4,"工资低于下限",IF(B16>参数设置!$B$5,"工资高于上限","工资在区间内"))) -> 待录入 | G16: =月度预算!M7 -> 2100 | H16: =月度预算!N7 -> 0 | I16: =月度预算!O7 -> 1400 | J16: =月度预算!U7
A17: =月度预算!A8 -> 46082 | B17: =月度预算!B8 -> 0 | C17: =月度预算!C8 -> 0 | D17: =月度预算!D8 -> 0 | E17: =月度预算!I8 -> 0 | F17: =IF(D17=0,"待录入",IF(B17<参数设置!$B$4,"工资低于下限",IF(B17>参数设置!$B$5,"工资高于上限","工资在区间内"))) -> 待录入 | G17: =月度预算!M8 -> 2100 | H17: =月度预算!N8 -> 0 | I17: =月度预算!O8 -> 1400 | J17: =月度预算!U8
A18: =月度预算!A9 -> 46113 | B18: =月度预算!B9 -> 0 | C18: =月度预算!C9 -> 0 | D18: =月度预算!D9 -> 0 | E18: =月度预算!I9 -> 0 | F18: =IF(D18=0,"待录入",IF(B18<参数设置!$B$4,"工资低于下限",IF(B18>参数设置!$B$5,"工资高于上限","工资在区间内"))) -> 待录入 | G18: =月度预算!M9 -> 2100 | H18: =月度预算!N9 -> 0 | I18: =月度预算!O9 -> 1400 | J18: =月度预算!U9
A19: =月度预算!A10 -> 46143 | B19: =月度预算!B10 -> 0 | C19: =月度预算!C10 -> 0 | D19: =月度预算!D10 -> 0 | E19: =月度预算!I10 -> 0 | F19: =IF(D19=0,"待录入",IF(B19<参数设置!$B$4,"工资低于下限",IF(B19>参数设置!$B$5,"工资高于上限","工资在区间内"))) -> 待录入 | G19: =月度预算!M10 -> 2100 | H19: =月度预算!N10 -> 0 | I19: =月度预算!O10 -> 1400 | J19: =月度预算!U10
A20: =月度预算!A11 -> 46174 | B20: =月度预算!B11 -> 0 | C20: =月度预算!C11 -> 0 | D20: =月度预算!D11 -> 0 | E20: =月度预算!I11 -> 0 | F20: =IF(D20=0,"待录入",IF(B20<参数设置!$B$4,"工资低于下限",IF(B20>参数设置!$B$5,"工资高于上限","工资在区间内"))) -> 待录入 | G20: =月度预算!M11 -> 2100 | H20: =月度预算!N11 -> 0 | I20: =月度预算!O11 -> 1400 | J20: =月度预算!U11
A21: =月度预算!A12 -> 46204 | B21: =月度预算!B12 -> 0 | C21: =月度预算!C12 -> 0 | D21: =月度预算!D12 -> 0 | E21: =月度预算!I12 -> 0 | F21: =IF(D21=0,"待录入",IF(B21<参数设置!$B$4,"工资低于下限",IF(B21>参数设置!$B$5,"工资高于上限","工资在区间内"))) -> 待录入 | G21: =月度预算!M12 -> 2100 | H21: =月度预算!N12 -> 0 | I21: =月度预算!O12 -> 1400 | J21: =月度预算!U12
A22: =月度预算!A13 -> 46235 | B22: =月度预算!B13 -> 0 | C22: =月度预算!C13 -> 0 | D22: =月度预算!D13 -> 0 | E22: =月度预算!I13 -> 0 | F22: =IF(D22=0,"待录入",IF(B22<参数设置!$B$4,"工资低于下限",IF(B22>参数设置!$B$5,"工资高于上限","工资在区间内"))) -> 待录入 | G22: =月度预算!M13 -> 2100 | H22: =月度预算!N13 -> 0 | I22: =月度预算!O13 -> 1400 | J22: =月度预算!U13
A23: =月度预算!A14 -> 46266 | B23: =月度预算!B14 -> 0 | C23: =月度预算!C14 -> 0 | D23: =月度预算!D14 -> 0 | E23: =月度预算!I14 -> 0 | F23: =IF(D23=0,"待录入",IF(B23<参数设置!$B$4,"工资低于下限",IF(B23>参数设置!$B$5,"工资高于上限","工资在区间内"))) -> 待录入 | G23: =月度预算!M14 -> 2100 | H23: =月度预算!N14 -> 0 | I23: =月度预算!O14 -> 1400 | J23: =月度预算!U14
A24: =月度预算!A15 -> 46296 | B24: =月度预算!B15 -> 0 | C24: =月度预算!C15 -> 0 | D24: =月度预算!D15 -> 0 | E24: =月度预算!I15 -> 0 | F24: =IF(D24=0,"待录入",IF(B24<参数设置!$B$4,"工资低于下限",IF(B24>参数设置!$B$5,"工资高于上限","工资在区间内"))) -> 待录入 | G24: =月度预算!M15 -> 2100 | H24: =月度预算!N15 -> 0 | I24: =月度预算!O15 -> 1400 | J24: =月度预算!U15
A25: =月度预算!A16 -> 46327 | B25: =月度预算!B16 -> 0 | C25: =月度预算!C16 -> 0 | D25: =月度预算!D16 -> 0 | E25: =月度预算!I16 -> 0 | F25: =IF(D25=0,"待录入",IF(B25<参数设置!$B$4,"工资低于下限",IF(B25>参数设置!$B$5,"工资高于上限","工资在区间内"))) -> 待录入 | G25: =月度预算!M16 -> 2100 | H25: =月度预算!N16 -> 0 | I25: =月度预算!O16 -> 1400 | J25: =月度预算!U16
A26: =月度预算!A17 -> 46357 | B26: =月度预算!B17 -> 0 | C26: =月度预算!C17 -> 0 | D26: =月度预算!D17 -> 0 | E26: =月度预算!I17 -> 0 | F26: =IF(D26=0,"待录入",IF(B26<参数设置!$B$4,"工资低于下限",IF(B26>参数设置!$B$5,"工资高于上限","工资在区间内"))) -> 待录入 | G26: =月度预算!M17 -> 2100 | H26: =月度预算!N17 -> 0 | I26: =月度预算!O17 -> 1400 | J26: =月度预算!U17

Sheet 月度预算
A1: 月度预算｜保守基准 + 额外收入自动分配
A3: 规则：基础预算只按保守预算基准计算；工资高于基准和非工资收入合并为额外收入，再按参数设置比例分配。
A5: 月份 | B5: 工资收入 | C5: 非工资收入 | D5: 实际总收入 | E5: 预算采用收入 | F5: 必要预算 | G5: 基础储蓄/还债预算 | H5: 基础弹性预算 | I5: 额外收入 | J5: 额外转储蓄/还债 | K5: 额外转准备金 | L5: 额外转弹性 | M5: 建议储蓄/还债 | N5: 建议准备金 | O5: 建议弹性 | P5: 实际必要 | Q5: 实际储蓄投资 | R5: 实际弹性 | S5: 实际还债 | T5: 实际准备金 | U5: 本月结余 | V5: 实际储蓄/偿债率 | W5: 状态 | X5: 备注
A6: =DATE(参数设置!$B$13,1,1) -> 46023 | B6: =SUMIFS(流水记录!$I$4:$I$503,流水记录!$B$4:$B$503,A6,流水记录!$D$4:$D$503,"收入",流水记录!$E$4:$E$503,"工资") -> 7800 | C6: =SUMIFS(流水记录!$I$4:$I$503,流水记录!$B$4:$B$503,A6,流水记录!$D$4:$D$503,"收入",流水记录!$E$4:$E$503,"<>工资") -> 1300 | D6: =B6+C6 -> 9100 | E6: =IF(D6=0,参数设置!$B$6,D6) -> 9100 | F6: =参数设置!$B$6*参数设置!$B$8 -> 3500 | G6: =参数设置!$B$6*参数设置!$B$9 -> 2100 | H6: =参数设置!$B$6*参数设置!$B$10 -> 1400 | I6: =MAX(0,E6-参数设置!$B$6) -> 2100 | J6: =I6*参数设置!$B$14 -> 1470 | K6: =I6*参数设置!$B$15 -> 420 | L6: =I6*参数设置!$B$16 -> 210 | M6: =G6+J6 -> 3570 | N6: =K6 -> 420 | O6: =H6+L6 -> 1610 | P6: =SUMIFS(流水记录!$I$4:$I$503,流水记录!$B$4:$B$503,A6,流水记录!$D$4:$D$503,"必要支出") -> 3900 | Q6: =SUMIFS(流水记录!$I$4:$I$503,流水记录!$B$4:$B$503,A6,流水记录!$D$4:$D$503,"储蓄投资") -> 2700 | R6: =SUMIFS(流水记录!$I$4:$I$503,流水记录!$B$4:$B$503,A6,流水记录!$D$4:$D$503,"弹性消费") -> 1000 | S6: =SUMIFS(流水记录!$I$4:$I$503,流水记录!$B$4:$B$503,A6,流水记录!$D$4:$D$503,"债务还款") -> 900 | T6: =SUMIFS(流水记录!$I$4:$I$503,流水记录!$B$4:$B$503,A6,流水记录!$D$4:$D$503,"专项准备金") -> 400 | U6: =IF(D6=0,"",D6-P6-Q6-R6-S6-T6) -> 200 | V6: =IFERROR((Q6+S6+T6)/D6,0) -> 0.43956044 | W6: =IF(D6=0,"待录入",IF(U6<0,"超支",IF(Q6+S6>=M6,"优秀",IF(Q6+S6+T6>=M6+N6,"正常","需要关注")))) -> 优秀
A7: =DATE(参数设置!$B$13,2,1) -> 46054 | B7: =SUMIFS(流水记录!$I$4:$I$503,流水记录!$B$4:$B$503,A7,流水记录!$D$4:$D$503,"收入",流水记录!$E$4:$E$503,"工资") -> 0 | C7: =SUMIFS(流水记录!$I$4:$I$503,流水记录!$B$4:$B$503,A7,流水记录!$D$4:$D$503,"收入",流水记录!$E$4:$E$503,"<>工资") -> 0 | D7: =B7+C7 -> 0 | E7: =IF(D7=0,参数设置!$B$6,D7) -> 7000 | F7: =参数设置!$B$6*参数设置!$B$8 -> 3500 | G7: =参数设置!$B$6*参数设置!$B$9 -> 2100 | H7: =参数设置!$B$6*参数设置!$B$10 -> 1400 | I7: =MAX(0,E7-参数设置!$B$6) -> 0 | J7: =I7*参数设置!$B$14 -> 0 | K7: =I7*参数设置!$B$15 -> 0 | L7: =I7*参数设置!$B$16 -> 0 | M7: =G7+J7 -> 2100 | N7: =K7 -> 0 | O7: =H7+L7 -> 1400 | P7: =SUMIFS(流水记录!$I$4:$I$503,流水记录!$B$4:$B$503,A7,流水记录!$D$4:$D$503,"必要支出") -> 0 | Q7: =SUMIFS(流水记录!$I$4:$I$503,流水记录!$B$4:$B$503,A7,流水记录!$D$4:$D$503,"储蓄投资") -> 0 | R7: =SUMIFS(流水记录!$I$4:$I$503,流水记录!$B$4:$B$503,A7,流水记录!$D$4:$D$503,"弹性消费") -> 0 | S7: =SUMIFS(流水记录!$I$4:$I$503,流水记录!$B$4:$B$503,A7,流水记录!$D$4:$D$503,"债务还款") -> 0 | T7: =SUMIFS(流水记录!$I$4:$I$503,流水记录!$B$4:$B$503,A7,流水记录!$D$4:$D$503,"专项准备金") -> 0 | U7: =IF(D7=0,"",D7-P7-Q7-R7-S7-T7) | V7: =IFERROR((Q7+S7+T7)/D7,0) -> 0 | W7: =IF(D7=0,"待录入",IF(U7<0,"超支",IF(Q7+S7>=M7,"优秀",IF(Q7+S7+T7>=M7+N7,"正常","需要关注")))) -> 待录入
A8: =DATE(参数设置!$B$13,3,1) -> 46082 | B8: =SUMIFS(流水记录!$I$4:$I$503,流水记录!$B$4:$B$503,A8,流水记录!$D$4:$D$503,"收入",流水记录!$E$4:$E$503,"工资") -> 0 | C8: =SUMIFS(流水记录!$I$4:$I$503,流水记录!$B$4:$B$503,A8,流水记录!$D$4:$D$503,"收入",流水记录!$E$4:$E$503,"<>工资") -> 0 | D8: =B8+C8 -> 0 | E8: =IF(D8=0,参数设置!$B$6,D8) -> 7000 | F8: =参数设置!$B$6*参数设置!$B$8 -> 3500 | G8: =参数设置!$B$6*参数设置!$B$9 -> 2100 | H8: =参数设置!$B$6*参数设置!$B$10 -> 1400 | I8: =MAX(0,E8-参数设置!$B$6) -> 0 | J8: =I8*参数设置!$B$14 -> 0 | K8: =I8*参数设置!$B$15 -> 0 | L8: =I8*参数设置!$B$16 -> 0 | M8: =G8+J8 -> 2100 | N8: =K8 -> 0 | O8: =H8+L8 -> 1400 | P8: =SUMIFS(流水记录!$I$4:$I$503,流水记录!$B$4:$B$503,A8,流水记录!$D$4:$D$503,"必要支出") -> 0 | Q8: =SUMIFS(流水记录!$I$4:$I$503,流水记录!$B$4:$B$503,A8,流水记录!$D$4:$D$503,"储蓄投资") -> 0 | R8: =SUMIFS(流水记录!$I$4:$I$503,流水记录!$B$4:$B$503,A8,流水记录!$D$4:$D$503,"弹性消费") -> 0 | S8: =SUMIFS(流水记录!$I$4:$I$503,流水记录!$B$4:$B$503,A8,流水记录!$D$4:$D$503,"债务还款") -> 0 | T8: =SUMIFS(流水记录!$I$4:$I$503,流水记录!$B$4:$B$503,A8,流水记录!$D$4:$D$503,"专项准备金") -> 0 | U8: =IF(D8=0,"",D8-P8-Q8-R8-S8-T8) | V8: =IFERROR((Q8+S8+T8)/D8,0) -> 0 | W8: =IF(D8=0,"待录入",IF(U8<0,"超支",IF(Q8+S8>=M8,"优秀",IF(Q8+S8+T8>=M8+N8,"正常","需要关注")))) -> 待录入
A9: =DATE(参数设置!$B$13,4,1) -> 46113 | B9: =SUMIFS(流水记录!$I$4:$I$503,流水记录!$B$4:$B$503,A9,流水记录!$D$4:$D$503,"收入",流水记录!$E$4:$E$503,"工资") -> 0 | C9: =SUMIFS(流水记录!$I$4:$I$503,流水记录!$B$4:$B$503,A9,流水记录!$D$4:$D$503,"收入",流水记录!$E$4:$E$503,"<>工资") -> 0 | D9: =B9+C9 -> 0 | E9: =IF(D9=0,参数设置!$B$6,D9) -> 7000 | F9: =参数设置!$B$6*参数设置!$B$8 -> 3500 | G9: =参数设置!$B$6*参数设置!$B$9 -> 2100 | H9: =参数设置!$B$6*参数设置!$B$10 -> 1400 | I9: =MAX(0,E9-参数设置!$B$6) -> 0 | J9: =I9*参数设置!$B$14 -> 0 | K9: =I9*参数设置!$B$15 -> 0 | L9: =I9*参数设置!$B$16 -> 0 | M9: =G9+J9 -> 2100 | N9: =K9 -> 0 | O9: =H9+L9 -> 1400 | P9: =SUMIFS(流水记录!$I$4:$I$503,流水记录!$B$4:$B$503,A9,流水记录!$D$4:$D$503,"必要支出") -> 0 | Q9: =SUMIFS(流水记录!$I$4:$I$503,流水记录!$B$4:$B$503,A9,流水记录!$D$4:$D$503,"储蓄投资") -> 0 | R9: =SUMIFS(流水记录!$I$4:$I$503,流水记录!$B$4:$B$503,A9,流水记录!$D$4:$D$503,"弹性消费") -> 0 | S9: =SUMIFS(流水记录!$I$4:$I$503,流水记录!$B$4:$B$503,A9,流水记录!$D$4:$D$503,"债务还款") -> 0 | T9: =SUMIFS(流水记录!$I$4:$I$503,流水记录!$B$4:$B$503,A9,流水记录!$D$4:$D$503,"专项准备金") -> 0 | U9: =IF(D9=0,"",D9-P9-Q9-R9-S9-T9) | V9: =IFERROR((Q9+S9+T9)/D9,0) -> 0 | W9: =IF(D9=0,"待录入",IF(U9<0,"超支",IF(Q9+S9>=M9,"优秀",IF(Q9+S9+T9>=M9+N9,"正常","需要关注")))) -> 待录入
A10: =DATE(参数设置!$B$13,5,1) -> 46143 | B10: =SUMIFS(流水记录!$I$4:$I$503,流水记录!$B$4:$B$503,A10,流水记录!$D$4:$D$503,"收入",流水记录!$E$4:$E$503,"工资") -> 0 | C10: =SUMIFS(流水记录!$I$4:$I$503,流水记录!$B$4:$B$503,A10,流水记录!$D$4:$D$503,"收入",流水记录!$E$4:$E$503,"<>工资") -> 0 | D10: =B10+C10 -> 0 | E10: =IF(D10=0,参数设置!$B$6,D10) -> 7000 | F10: =参数设置!$B$6*参数设置!$B$8 -> 3500 | G10: =参数设置!$B$6*参数设置!$B$9 -> 2100 | H10: =参数设置!$B$6*参数设置!$B$10 -> 1400 | I10: =MAX(0,E10-参数设置!$B$6) -> 0 | J10: =I10*参数设置!$B$14 -> 0 | K10: =I10*参数设置!$B$15 -> 0 | L10: =I10*参数设置!$B$16 -> 0 | M10: =G10+J10 -> 2100 | N10: =K10 -> 0 | O10: =H10+L10 -> 1400 | P10: =SUMIFS(流水记录!$I$4:$I$503,流水记录!$B$4:$B$503,A10,流水记录!$D$4:$D$503,"必要支出") -> 0 | Q10: =SUMIFS(流水记录!$I$4:$I$503,流水记录!$B$4:$B$503,A10,流水记录!$D$4:$D$503,"储蓄投资") -> 0 | R10: =SUMIFS(流水记录!$I$4:$I$503,流水记录!$B$4:$B$503,A10,流水记录!$D$4:$D$503,"弹性消费") -> 0 | S10: =SUMIFS(流水记录!$I$4:$I$503,流水记录!$B$4:$B$503,A10,流水记录!$D$4:$D$503,"债务还款") -> 0 | T10: =SUMIFS(流水记录!$I$4:$I$503,流水记录!$B$4:$B$503,A10,流水记录!$D$4:$D$503,"专项准备金") -> 0 | U10: =IF(D10=0,"",D10-P10-Q10-R10-S10-T10) | V10: =IFERROR((Q10+S10+T10)/D10,0) -> 0 | W10: =IF(D10=0,"待录入",IF(U10<0,"超支",IF(Q10+S10>=M10,"优秀",IF(Q10+S10+T10>=M10+N10,"正常","需要关注")))) -> 待录入
A11: =DATE(参数设置!$B$13,6,1) -> 46174 | B11: =SUMIFS(流水记录!$I$4:$I$503,流水记录!$B$4:$B$503,A11,流水记录!$D$4:$D$503,"收入",流水记录!$E$4:$E$503,"工资") -> 0 | C11: =SUMIFS(流水记录!$I$4:$I$503,流水记录!$B$4:$B$503,A11,流水记录!$D$4:$D$503,"收入",流水记录!$E$4:$E$503,"<>工资") -> 0 | D11: =B11+C11 -> 0 | E11: =IF(D11=0,参数设置!$B$6,D11) -> 7000 | F11: =参数设置!$B$6*参数设置!$B$8 -> 3500 | G11: =参数设置!$B$6*参数设置!$B$9 -> 2100 | H11: =参数设置!$B$6*参数设置!$B$10 -> 1400 | I11: =MAX(0,E11-参数设置!$B$6) -> 0 | J11: =I11*参数设置!$B$14 -> 0 | K11: =I11*参数设置!$B$15 -> 0 | L11: =I11*参数设置!$B$16 -> 0 | M11: =G11+J11 -> 2100 | N11: =K11 -> 0 | O11: =H11+L11 -> 1400 | P11: =SUMIFS(流水记录!$I$4:$I$503,流水记录!$B$4:$B$503,A11,流水记录!$D$4:$D$503,"必要支出") -> 0 | Q11: =SUMIFS(流水记录!$I$4:$I$503,流水记录!$B$4:$B$503,A11,流水记录!$D$4:$D$503,"储蓄投资") -> 0 | R11: =SUMIFS(流水记录!$I$4:$I$503,流水记录!$B$4:$B$503,A11,流水记录!$D$4:$D$503,"弹性消费") -> 0 | S11: =SUMIFS(流水记录!$I$4:$I$503,流水记录!$B$4:$B$503,A11,流水记录!$D$4:$D$503,"债务还款") -> 0 | T11: =SUMIFS(流水记录!$I$4:$I$503,流水记录!$B$4:$B$503,A11,流水记录!$D$4:$D$503,"专项准备金") -> 0 | U11: =IF(D11=0,"",D11-P11-Q11-R11-S11-T11) | V11: =IFERROR((Q11+S11+T11)/D11,0) -> 0 | W11: =IF(D11=0,"待录入",IF(U11<0,"超支",IF(Q11+S11>=M11,"优秀",IF(Q11+S11+T11>=M11+N11,"正常","需要关注")))) -> 待录入
A12: =DATE(参数设置!$B$13,7,1) -> 46204 | B12: =SUMIFS(流水记录!$I$4:$I$503,流水记录!$B$4:$B$503,A12,流水记录!$D$4:$D$503,"收入",流水记录!$E$4:$E$503,"工资") -> 0 | C12: =SUMIFS(流水记录!$I$4:$I$503,流水记录!$B$4:$B$503,A12,流水记录!$D$4:$D$503,"收入",流水记录!$E$4:$E$503,"<>工资") -> 0 | D12: =B12+C12 -> 0 | E12: =IF(D12=0,参数设置!$B$6,D12) -> 7000 | F12: =参数设置!$B$6*参数设置!$B$8 -> 3500 | G12: =参数设置!$B$6*参数设置!$B$9 -> 2100 | H12: =参数设置!$B$6*参数设置!$B$10 -> 1400 | I12: =MAX(0,E12-参数设置!$B$6) -> 0 | J12: =I12*参数设置!$B$14 -> 0 | K12: =I12*参数设置!$B$15 -> 0 | L12: =I12*参数设置!$B$16 -> 0 | M12: =G12+J12 -> 2100 | N12: =K12 -> 0 | O12: =H12+L12 -> 1400 | P12: =SUMIFS(流水记录!$I$4:$I$503,流水记录!$B$4:$B$503,A12,流水记录!$D$4:$D$503,"必要支出") -> 0 | Q12: =SUMIFS(流水记录!$I$4:$I$503,流水记录!$B$4:$B$503,A12,流水记录!$D$4:$D$503,"储蓄投资") -> 0 | R12: =SUMIFS(流水记录!$I$4:$I$503,流水记录!$B$4:$B$503,A12,流水记录!$D$4:$D$503,"弹性消费") -> 0 | S12: =SUMIFS(流水记录!$I$4:$I$503,流水记录!$B$4:$B$503,A12,流水记录!$D$4:$D$503,"债务还款") -> 0 | T12: =SUMIFS(流水记录!$I$4:$I$503,流水记录!$B$4:$B$503,A12,流水记录!$D$4:$D$503,"专项准备金") -> 0 | U12: =IF(D12=0,"",D12-P12-Q12-R12-S12-T12) | V12: =IFERROR((Q12+S12+T12)/D12,0) -> 0 | W12: =IF(D12=0,"待录入",IF(U12<0,"超支",IF(Q12+S12>=M12,"优秀",IF(Q12+S12+T12>=M12+N12,"正常","需要关注")))) -> 待录入
A13: =DATE(参数设置!$B$13,8,1) -> 46235 | B13: =SUMIFS(流水记录!$I$4:$I$503,流水记录!$B$4:$B$503,A13,流水记录!$D$4:$D$503,"收入",流水记录!$E$4:$E$503,"工资") -> 0 | C13: =SUMIFS(流水记录!$I$4:$I$503,流水记录!$B$4:$B$503,A13,流水记录!$D$4:$D$503,"收入",流水记录!$E$4:$E$503,"<>工资") -> 0 | D13: =B13+C13 -> 0 | E13: =IF(D13=0,参数设置!$B$6,D13) -> 7000 | F13: =参数设置!$B$6*参数设置!$B$8 -> 3500 | G13: =参数设置!$B$6*参数设置!$B$9 -> 2100 | H13: =参数设置!$B$6*参数设置!$B$10 -> 1400 | I13: =MAX(0,E13-参数设置!$B$6) -> 0 | J13: =I13*参数设置!$B$14 -> 0 | K13: =I13*参数设置!$B$15 -> 0 | L13: =I13*参数设置!$B$16 -> 0 | M13: =G13+J13 -> 2100 | N13: =K13 -> 0 | O13: =H13+L13 -> 1400 | P13: =SUMIFS(流水记录!$I$4:$I$503,流水记录!$B$4:$B$503,A13,流水记录!$D$4:$D$503,"必要支出") -> 0 | Q13: =SUMIFS(流水记录!$I$4:$I$503,流水记录!$B$4:$B$503,A13,流水记录!$D$4:$D$503,"储蓄投资") -> 0 | R13: =SUMIFS(流水记录!$I$4:$I$503,流水记录!$B$4:$B$503,A13,流水记录!$D$4:$D$503,"弹性消费") -> 0 | S13: =SUMIFS(流水记录!$I$4:$I$503,流水记录!$B$4:$B$503,A13,流水记录!$D$4:$D$503,"债务还款") -> 0 | T13: =SUMIFS(流水记录!$I$4:$I$503,流水记录!$B$4:$B$503,A13,流水记录!$D$4:$D$503,"专项准备金") -> 0 | U13: =IF(D13=0,"",D13-P13-Q13-R13-S13-T13) | V13: =IFERROR((Q13+S13+T13)/D13,0) -> 0 | W13: =IF(D13=0,"待录入",IF(U13<0,"超支",IF(Q13+S13>=M13,"优秀",IF(Q13+S13+T13>=M13+N13,"正常","需要关注")))) -> 待录入
A14: =DATE(参数设置!$B$13,9,1) -> 46266 | B14: =SUMIFS(流水记录!$I$4:$I$503,流水记录!$B$4:$B$503,A14,流水记录!$D$4:$D$503,"收入",流水记录!$E$4:$E$503,"工资") -> 0 | C14: =SUMIFS(流水记录!$I$4:$I$503,流水记录!$B$4:$B$503,A14,流水记录!$D$4:$D$503,"收入",流水记录!$E$4:$E$503,"<>工资") -> 0 | D14: =B14+C14 -> 0 | E14: =IF(D14=0,参数设置!$B$6,D14) -> 7000 | F14: =参数设置!$B$6*参数设置!$B$8 -> 3500 | G14: =参数设置!$B$6*参数设置!$B$9 -> 2100 | H14: =参数设置!$B$6*参数设置!$B$10 -> 1400 | I14: =MAX(0,E14-参数设置!$B$6) -> 0 | J14: =I14*参数设置!$B$14 -> 0 | K14: =I14*参数设置!$B$15 -> 0 | L14: =I14*参数设置!$B$16 -> 0 | M14: =G14+J14 -> 2100 | N14: =K14 -> 0 | O14: =H14+L14 -> 1400 | P14: =SUMIFS(流水记录!$I$4:$I$503,流水记录!$B$4:$B$503,A14,流水记录!$D$4:$D$503,"必要支出") -> 0 | Q14: =SUMIFS(流水记录!$I$4:$I$503,流水记录!$B$4:$B$503,A14,流水记录!$D$4:$D$503,"储蓄投资") -> 0 | R14: =SUMIFS(流水记录!$I$4:$I$503,流水记录!$B$4:$B$503,A14,流水记录!$D$4:$D$503,"弹性消费") -> 0 | S14: =SUMIFS(流水记录!$I$4:$I$503,流水记录!$B$4:$B$503,A14,流水记录!$D$4:$D$503,"债务还款") -> 0 | T14: =SUMIFS(流水记录!$I$4:$I$503,流水记录!$B$4:$B$503,A14,流水记录!$D$4:$D$503,"专项准备金") -> 0 | U14: =IF(D14=0,"",D14-P14-Q14-R14-S14-T14) | V14: =IFERROR((Q14+S14+T14)/D14,0) -> 0 | W14: =IF(D14=0,"待录入",IF(U14<0,"超支",IF(Q14+S14>=M14,"优秀",IF(Q14+S14+T14>=M14+N14,"正常","需要关注")))) -> 待录入
A15: =DATE(参数设置!$B$13,10,1) -> 46296 | B15: =SUMIFS(流水记录!$I$4:$I$503,流水记录!$B$4:$B$503,A15,流水记录!$D$4:$D$503,"收入",流水记录!$E$4:$E$503,"工资") -> 0 | C15: =SUMIFS(流水记录!$I$4:$I$503,流水记录!$B$4:$B$503,A15,流水记录!$D$4:$D$503,"收入",流水记录!$E$4:$E$503,"<>工资") -> 0 | D15: =B15+C15 -> 0 | E15: =IF(D15=0,参数设置!$B$6,D15) -> 7000 | F15: =参数设置!$B$6*参数设置!$B$8 -> 3500 | G15: =参数设置!$B$6*参数设置!$B$9 -> 2100 | H15: =参数设置!$B$6*参数设置!$B$10 -> 1400 | I15: =MAX(0,E15-参数设置!$B$6) -> 0 | J15: =I15*参数设置!$B$14 -> 0 | K15: =I15*参数设置!$B$15 -> 0 | L15: =I15*参数设置!$B$16 -> 0 | M15: =G15+J15 -> 2100 | N15: =K15 -> 0 | O15: =H15+L15 -> 1400 | P15: =SUMIFS(流水记录!$I$4:$I$503,流水记录!$B$4:$B$503,A15,流水记录!$D$4:$D$503,"必要支出") -> 0 | Q15: =SUMIFS(流水记录!$I$4:$I$503,流水记录!$B$4:$B$503,A15,流水记录!$D$4:$D$503,"储蓄投资") -> 0 | R15: =SUMIFS(流水记录!$I$4:$I$503,流水记录!$B$4:$B$503,A15,流水记录!$D$4:$D$503,"弹性消费") -> 0 | S15: =SUMIFS(流水记录!$I$4:$I$503,流水记录!$B$4:$B$503,A15,流水记录!$D$4:$D$503,"债务还款") -> 0 | T15: =SUMIFS(流水记录!$I$4:$I$503,流水记录!$B$4:$B$503,A15,流水记录!$D$4:$D$503,"专项准备金") -> 0 | U15: =IF(D15=0,"",D15-P15-Q15-R15-S15-T15) | V15: =IFERROR((Q15+S15+T15)/D15,0) -> 0 | W15: =IF(D15=0,"待录入",IF(U15<0,"超支",IF(Q15+S15>=M15,"优秀",IF(Q15+S15+T15>=M15+N15,"正常","需要关注")))) -> 待录入
A16: =DATE(参数设置!$B$13,11,1) -> 46327 | B16: =SUMIFS(流水记录!$I$4:$I$503,流水记录!$B$4:$B$503,A16,流水记录!$D$4:$D$503,"收入",流水记录!$E$4:$E$503,"工资") -> 0 | C16: =SUMIFS(流水记录!$I$4:$I$503,流水记录!$B$4:$B$503,A16,流水记录!$D$4:$D$503,"收入",流水记录!$E$4:$E$503,"<>工资") -> 0 | D16: =B16+C16 -> 0 | E16: =IF(D16=0,参数设置!$B$6,D16) -> 7000 | F16: =参数设置!$B$6*参数设置!$B$8 -> 3500 | G16: =参数设置!$B$6*参数设置!$B$9 -> 2100 | H16: =参数设置!$B$6*参数设置!$B$10 -> 1400 | I16: =MAX(0,E16-参数设置!$B$6) -> 0 | J16: =I16*参数设置!$B$14 -> 0 | K16: =I16*参数设置!$B$15 -> 0 | L16: =I16*参数设置!$B$16 -> 0 | M16: =G16+J16 -> 2100 | N16: =K16 -> 0 | O16: =H16+L16 -> 1400 | P16: =SUMIFS(流水记录!$I$4:$I$503,流水记录!$B$4:$B$503,A16,流水记录!$D$4:$D$503,"必要支出") -> 0 | Q16: =SUMIFS(流水记录!$I$4:$I$503,流水记录!$B$4:$B$503,A16,流水记录!$D$4:$D$503,"储蓄投资") -> 0 | R16: =SUMIFS(流水记录!$I$4:$I$503,流水记录!$B$4:$B$503,A16,流水记录!$D$4:$D$503,"弹性消费") -> 0 | S16: =SUMIFS(流水记录!$I$4:$I$503,流水记录!$B$4:$B$503,A16,流水记录!$D$4:$D$503,"债务还款") -> 0 | T16: =SUMIFS(流水记录!$I$4:$I$503,流水记录!$B$4:$B$503,A16,流水记录!$D$4:$D$503,"专项准备金") -> 0 | U16: =IF(D16=0,"",D16-P16-Q16-R16-S16-T16) | V16: =IFERROR((Q16+S16+T16)/D16,0) -> 0 | W16: =IF(D16=0,"待录入",IF(U16<0,"超支",IF(Q16+S16>=M16,"优秀",IF(Q16+S16+T16>=M16+N16,"正常","需要关注")))) -> 待录入
A17: =DATE(参数设置!$B$13,12,1) -> 46357 | B17: =SUMIFS(流水记录!$I$4:$I$503,流水记录!$B$4:$B$503,A17,流水记录!$D$4:$D$503,"收入",流水记录!$E$4:$E$503,"工资") -> 0 | C17: =SUMIFS(流水记录!$I$4:$I$503,流水记录!$B$4:$B$503,A17,流水记录!$D$4:$D$503,"收入",流水记录!$E$4:$E$503,"<>工资") -> 0 | D17: =B17+C17 -> 0 | E17: =IF(D17=0,参数设置!$B$6,D17) -> 7000 | F17: =参数设置!$B$6*参数设置!$B$8 -> 3500 | G17: =参数设置!$B$6*参数设置!$B$9 -> 2100 | H17: =参数设置!$B$6*参数设置!$B$10 -> 1400 | I17: =MAX(0,E17-参数设置!$B$6) -> 0 | J17: =I17*参数设置!$B$14 -> 0 | K17: =I17*参数设置!$B$15 -> 0 | L17: =I17*参数设置!$B$16 -> 0 | M17: =G17+J17 -> 2100 | N17: =K17 -> 0 | O17: =H17+L17 -> 1400 | P17: =SUMIFS(流水记录!$I$4:$I$503,流水记录!$B$4:$B$503,A17,流水记录!$D$4:$D$503,"必要支出") -> 0 | Q17: =SUMIFS(流水记录!$I$4:$I$503,流水记录!$B$4:$B$503,A17,流水记录!$D$4:$D$503,"储蓄投资") -> 0 | R17: =SUMIFS(流水记录!$I$4:$I$503,流水记录!$B$4:$B$503,A17,流水记录!$D$4:$D$503,"弹性消费") -> 0 | S17: =SUMIFS(流水记录!$I$4:$I$503,流水记录!$B$4:$B$503,A17,流水记录!$D$4:$D$503,"债务还款") -> 0 | T17: =SUMIFS(流水记录!$I$4:$I$503,流水记录!$B$4:$B$503,A17,流水记录!$D$4:$D$503,"专项准备金") -> 0 | U17: =IF(D17=0,"",D17-P17-Q17-R17-S17-T17) | V17: =IFERROR((Q17+S17+T17)/D17,0) -> 0 | W17: =IF(D17=0,"待录入",IF(U17<0,"超支",IF(Q17+S17>=M17,"优秀",IF(Q17+S17+T17>=M17+N17,"正常","需要关注")))) -> 待录入

Sheet 月度仪表盘
A1: 月度仪表盘｜一页看懂现金流、额外收入、应急金和资产
A3: 查看月份 | B3: =月度预算!$A$6 -> 46023
A5: 工资收入 | B5: 非工资收入 | C5: 总收入 | D5: 额外收入 | E5: 本月结余 | F5: 储蓄/偿债率 | G5: 应急金达成 | H5: 净资产 | J5: 本月执行建议
A6: =INDEX(月度预算!$B$6:$B$17,MATCH($B$3,月度预算!$A$6:$A$17,0)) -> 7800 | B6: =INDEX(月度预算!$C$6:$C$17,MATCH($B$3,月度预算!$A$6:$A$17,0)) -> 1300 | C6: =INDEX(月度预算!$D$6:$D$17,MATCH($B$3,月度预算!$A$6:$A$17,0)) -> 9100 | D6: =INDEX(月度预算!$I$6:$I$17,MATCH($B$3,月度预算!$A$6:$A$17,0)) -> 2100 | E6: =INDEX(月度预算!$U$6:$U$17,MATCH($B$3,月度预算!$A$6:$A$17,0)) -> 200 | F6: =INDEX(月度预算!$V$6:$V$17,MATCH($B$3,月度预算!$A$6:$A$17,0)) -> 0.43956044 | G6: =应急金!$B$12 -> 0.1 | H6: =资产配置!$B$11-债务管理!$B$24 -> 15200 | J6: 低收入月 | K6: 按保守基准控制必要支出和弹性消费。
J7: 高收入月 | K7: 额外收入优先补应急金、还高息债、定投。
A8: 本月预算 vs 实际 | J8: 不定期收入 | K8: 不要直接并入日常消费，先按比例分配。
A9: 类别 | B9: 建议 | C9: 实际 | D9: 差额 | J9: 复盘重点 | K9: 看结余、储蓄/偿债率和应急金达成率。
A10: 必要支出 | B10: =INDEX(月度预算!$F$6:$F$17,MATCH($B$3,月度预算!$A$6:$A$17,0)) -> 3500 | C10: =INDEX(月度预算!$P$6:$P$17,MATCH($B$3,月度预算!$A$6:$A$17,0)) -> 3900 | D10: =C10-B10 -> 400
A11: 储蓄/投资/还债 | B11: =INDEX(月度预算!$M$6:$M$17,MATCH($B$3,月度预算!$A$6:$A$17,0)) -> 3570 | C11: =INDEX(月度预算!$Q$6:$Q$17,MATCH($B$3,月度预算!$A$6:$A$17,0))+INDEX(月度预算!$S$6:$S$17,MATCH($B$3,月度预算!$A$6:$A$17,0)) -> 3600 | D11: =C11-B11 -> 30
A12: 专项准备金 | B12: =INDEX(月度预算!$N$6:$N$17,MATCH($B$3,月度预算!$A$6:$A$17,0)) -> 420 | C12: =INDEX(月度预算!$T$6:$T$17,MATCH($B$3,月度预算!$A$6:$A$17,0)) -> 400 | D12: =C12-B12 -> -20
A13: 弹性消费 | B13: =INDEX(月度预算!$O$6:$O$17,MATCH($B$3,月度预算!$A$6:$A$17,0)) -> 1610 | C13: =INDEX(月度预算!$R$6:$R$17,MATCH($B$3,月度预算!$A$6:$A$17,0)) -> 1000 | D13: =C13-B13 -> -610
A16: 月份 | B16: 总收入 | C16: 结余 | D16: 储蓄/偿债率
A17: =TEXT(月度预算!A6,"yyyy-mm") -> 2026-01 | B17: =IF(月度预算!D6=0,"",月度预算!D6) -> 9100 | C17: =IF(月度预算!D6=0,"",月度预算!U6) -> 200 | D17: =IF(月度预算!D6=0,"",月度预算!V6) -> 0.43956044
A18: =TEXT(月度预算!A7,"yyyy-mm") -> 2026-02 | B18: =IF(月度预算!D7=0,"",月度预算!D7) | C18: =IF(月度预算!D7=0,"",月度预算!U7) | D18: =IF(月度预算!D7=0,"",月度预算!V7) | F18: 资产类别 | G18: 当前金额 | H18: 当前比例 | K18: 债务 | L18: 余额 | M18: 年利率 | N18: 建议
A19: =TEXT(月度预算!A8,"yyyy-mm") -> 2026-03 | B19: =IF(月度预算!D8=0,"",月度预算!D8) | C19: =IF(月度预算!D8=0,"",月度预算!U8) | D19: =IF(月度预算!D8=0,"",月度预算!V8) | F19: =资产配置!A4 -> 现金/活期 | G19: =资产配置!B4 -> 3000 | H19: =资产配置!D4 -> 0.19736842 | K19: =IF(债务管理!A4="","",债务管理!A4) -> 信用卡分期 | L19: =IF(K19="","",债务管理!B4) -> 0 | M19: =IF(K19="","",债务管理!C4) -> 0 | N19: =IF(K19="","",债务管理!I4)
A20: =TEXT(月度预算!A9,"yyyy-mm") -> 2026-04 | B20: =IF(月度预算!D9=0,"",月度预算!D9) | C20: =IF(月度预算!D9=0,"",月度预算!U9) | D20: =IF(月度预算!D9=0,"",月度预算!V9) | F20: =资产配置!A5 -> 应急金 | G20: =资产配置!B5 -> 1200 | H20: =资产配置!D5 -> 0.078947368 | K20: =IF(债务管理!A5="","",债务管理!A5) -> 消费贷 | L20: =IF(K20="","",债务管理!B5) -> 0 | M20: =IF(K20="","",债务管理!C5) -> 0 | N20: =IF(K20="","",债务管理!I5)
A21: =TEXT(月度预算!A10,"yyyy-mm") -> 2026-05 | B21: =IF(月度预算!D10=0,"",月度预算!D10) | C21: =IF(月度预算!D10=0,"",月度预算!U10) | D21: =IF(月度预算!D10=0,"",月度预算!V10) | F21: =资产配置!A6 -> 债券/固收 | G21: =资产配置!B6 -> 4000 | H21: =资产配置!D6 -> 0.26315789 | K21: =IF(债务管理!A6="","",债务管理!A6) -> 低息房贷/其他 | L21: =IF(K21="","",债务管理!B6) -> 0 | M21: =IF(K21="","",债务管理!C6) -> 0.045 | N21: =IF(K21="","",债务管理!I6)
A22: =TEXT(月度预算!A11,"yyyy-mm") -> 2026-06 | B22: =IF(月度预算!D11=0,"",月度预算!D11) | C22: =IF(月度预算!D11=0,"",月度预算!U11) | D22: =IF(月度预算!D11=0,"",月度预算!V11) | F22: =资产配置!A7 -> 权益基金/股票 | G22: =资产配置!B7 -> 6000 | H22: =资产配置!D7 -> 0.39473684
A23: =TEXT(月度预算!A12,"yyyy-mm") -> 2026-07 | B23: =IF(月度预算!D12=0,"",月度预算!D12) | C23: =IF(月度预算!D12=0,"",月度预算!U12) | D23: =IF(月度预算!D12=0,"",月度预算!V12) | F23: =资产配置!A8 -> 黄金/商品 | G23: =资产配置!B8 -> 1000 | H23: =资产配置!D8 -> 0.065789474
A24: =TEXT(月度预算!A13,"yyyy-mm") -> 2026-08 | B24: =IF(月度预算!D13=0,"",月度预算!D13) | C24: =IF(月度预算!D13=0,"",月度预算!U13) | D24: =IF(月度预算!D13=0,"",月度预算!V13) | F24: =资产配置!A9 -> 其他 | G24: =资产配置!B9 -> 0 | H24: =资产配置!D9 -> 0
A25: =TEXT(月度预算!A14,"yyyy-mm") -> 2026-09 | B25: =IF(月度预算!D14=0,"",月度预算!D14) | C25: =IF(月度预算!D14=0,"",月度预算!U14) | D25: =IF(月度预算!D14=0,"",月度预算!V14)
A26: =TEXT(月度预算!A15,"yyyy-mm") -> 2026-10 | B26: =IF(月度预算!D15=0,"",月度预算!D15) | C26: =IF(月度预算!D15=0,"",月度预算!U15) | D26: =IF(月度预算!D15=0,"",月度预算!V15)
A27: =TEXT(月度预算!A16,"yyyy-mm") -> 2026-11 | B27: =IF(月度预算!D16=0,"",月度预算!D16) | C27: =IF(月度预算!D16=0,"",月度预算!U16) | D27: =IF(月度预算!D16=0,"",月度预算!V16)
A28: =TEXT(月度预算!A17,"yyyy-mm") -> 2026-12 | B28: =IF(月度预算!D17=0,"",月度预算!D17) | C28: =IF(月度预算!D17=0,"",月度预算!U17) | D28: =IF(月度预算!D17=0,"",月度预算!V17)

Sheet 应急金
A1: 应急金｜先补安全垫，再做高波动投资
A3: 核心指标 | D3: 12个月补足计划
A4: 项目 | B4: 数值 | D4: 月份 | E4: 计划存入 | F4: 实际存入 | G4: 累计达成率
A5: 每月必要生活费 | B5: =参数设置!$B$12 -> 4000 | D5: =月度预算!A6 -> 46023 | E5: =IF($B$11<=0,0,ROUNDUP($B$11/12,0)) -> 900 | F5: =SUMIFS(流水记录!$I$4:$I$503,流水记录!$B$4:$B$503,D5,流水记录!$E$4:$E$503,"应急金") -> 1200 | G5: =IFERROR(($B$8+SUM($F$5:F5))/$B$7,0) -> 0.1
A6: 目标月数 | B6: =参数设置!$B$11 -> 3 | D6: =月度预算!A7 -> 46054 | E6: =IF($B$11<=0,0,ROUNDUP($B$11/12,0)) -> 900 | F6: =SUMIFS(流水记录!$I$4:$I$503,流水记录!$B$4:$B$503,D6,流水记录!$E$4:$E$503,"应急金") -> 0 | G6: =IFERROR(($B$8+SUM($F$5:F6))/$B$7,0) -> 0.1
A7: 目标金额 | B7: =B5*B6 -> 12000 | D7: =月度预算!A8 -> 46082 | E7: =IF($B$11<=0,0,ROUNDUP($B$11/12,0)) -> 900 | F7: =SUMIFS(流水记录!$I$4:$I$503,流水记录!$B$4:$B$503,D7,流水记录!$E$4:$E$503,"应急金") -> 0 | G7: =IFERROR(($B$8+SUM($F$5:F7))/$B$7,0) -> 0.1
A8: 期初应急金余额（手填） | B8: 0 | D8: =月度预算!A9 -> 46113 | E8: =IF($B$11<=0,0,ROUNDUP($B$11/12,0)) -> 900 | F8: =SUMIFS(流水记录!$I$4:$I$503,流水记录!$B$4:$B$503,D8,流水记录!$E$4:$E$503,"应急金") -> 0 | G8: =IFERROR(($B$8+SUM($F$5:F8))/$B$7,0) -> 0.1
A9: 已记录存入 | B9: =SUMIFS(流水记录!$I$4:$I$503,流水记录!$E$4:$E$503,"应急金") -> 1200 | D9: =月度预算!A10 -> 46143 | E9: =IF($B$11<=0,0,ROUNDUP($B$11/12,0)) -> 900 | F9: =SUMIFS(流水记录!$I$4:$I$503,流水记录!$B$4:$B$503,D9,流水记录!$E$4:$E$503,"应急金") -> 0 | G9: =IFERROR(($B$8+SUM($F$5:F9))/$B$7,0) -> 0.1
A10: 当前应急金余额 | B10: =B8+B9 -> 1200 | D10: =月度预算!A11 -> 46174 | E10: =IF($B$11<=0,0,ROUNDUP($B$11/12,0)) -> 900 | F10: =SUMIFS(流水记录!$I$4:$I$503,流水记录!$B$4:$B$503,D10,流水记录!$E$4:$E$503,"应急金") -> 0 | G10: =IFERROR(($B$8+SUM($F$5:F10))/$B$7,0) -> 0.1
A11: 缺口 | B11: =MAX(B7-B10,0) -> 10800 | D11: =月度预算!A12 -> 46204 | E11: =IF($B$11<=0,0,ROUNDUP($B$11/12,0)) -> 900 | F11: =SUMIFS(流水记录!$I$4:$I$503,流水记录!$B$4:$B$503,D11,流水记录!$E$4:$E$503,"应急金") -> 0 | G11: =IFERROR(($B$8+SUM($F$5:F11))/$B$7,0) -> 0.1
A12: 达成率 | B12: =IFERROR(B10/B7,0) -> 0.1 | D12: =月度预算!A13 -> 46235 | E12: =IF($B$11<=0,0,ROUNDUP($B$11/12,0)) -> 900 | F12: =SUMIFS(流水记录!$I$4:$I$503,流水记录!$B$4:$B$503,D12,流水记录!$E$4:$E$503,"应急金") -> 0 | G12: =IFERROR(($B$8+SUM($F$5:F12))/$B$7,0) -> 0.1
A13: 建议动作 | B13: =IF(B12>=1,"已达成：保持流动性",IF(B10>=B5,"继续补足到目标月数","先补足1个月生活费")) -> 先补足1个月生活费 | D13: =月度预算!A14 -> 46266 | E13: =IF($B$11<=0,0,ROUNDUP($B$11/12,0)) -> 900 | F13: =SUMIFS(流水记录!$I$4:$I$503,流水记录!$B$4:$B$503,D13,流水记录!$E$4:$E$503,"应急金") -> 0 | G13: =IFERROR(($B$8+SUM($F$5:F13))/$B$7,0) -> 0.1
D14: =月度预算!A15 -> 46296 | E14: =IF($B$11<=0,0,ROUNDUP($B$11/12,0)) -> 900 | F14: =SUMIFS(流水记录!$I$4:$I$503,流水记录!$B$4:$B$503,D14,流水记录!$E$4:$E$503,"应急金") -> 0 | G14: =IFERROR(($B$8+SUM($F$5:F14))/$B$7,0) -> 0.1
D15: =月度预算!A16 -> 46327 | E15: =IF($B$11<=0,0,ROUNDUP($B$11/12,0)) -> 900 | F15: =SUMIFS(流水记录!$I$4:$I$503,流水记录!$B$4:$B$503,D15,流水记录!$E$4:$E$503,"应急金") -> 0 | G15: =IFERROR(($B$8+SUM($F$5:F15))/$B$7,0) -> 0.1
D16: =月度预算!A17 -> 46357 | E16: =IF($B$11<=0,0,ROUNDUP($B$11/12,0)) -> 900 | F16: =SUMIFS(流水记录!$I$4:$I$503,流水记录!$B$4:$B$503,D16,流水记录!$E$4:$E$503,"应急金") -> 0 | G16: =IFERROR(($B$8+SUM($F$5:F16))/$B$7,0) -> 0.1

Sheet 债务管理
A1: 债务管理｜优先处理高息债务
A3: 债务名称 | B3: 当前余额 | C3: 年利率 | D3: 最低月还款 | E3: 额外还款 | F3: 计划月还款 | G3: 优先级 | H3: 预计还清月数 | I3: 建议
A4: 信用卡分期 | B4: 0 | C4: 0 | D4: 0 | E4: 0 | F4: 0 | G4: =IF(B4>0,RANK(C4,$C$4:$C$21,0),"") | H4: =IF(B4<=0,"",IF(F4<=B4*C4/12,"还款不足",ROUNDUP(NPER(C4/12,-F4,B4),0))) | I4: =IF(B4<=0,"",IF(G4=1,"优先偿还","维持最低还款"))
A5: 消费贷 | B5: 0 | C5: 0 | D5: 0 | E5: 0 | F5: 0 | I5: =IF(B5<=0,"",IF(G5=1,"优先偿还","维持最低还款"))
A6: 低息房贷/其他 | B6: 0 | C6: 0.045 | D6: 0 | E6: 0 | F6: =D6+E6 -> 0 | G6: =IF(B6>0,RANK(C6,$C$4:$C$21,0),"") | H6: =IF(B6<=0,"",IF(F6<=B6*C6/12,"还款不足",ROUNDUP(NPER(C6/12,-F6,B6),0))) | I6: =IF(B6<=0,"",IF(G6=1,"优先偿还","维持最低还款"))
B7: 0 | C7: 0 | D7: 0 | E7: 0 | F7: =D7+E7 -> 0 | G7: =IF(B7>0,RANK(C7,$C$4:$C$21,0),"") | H7: =IF(B7<=0,"",IF(F7<=B7*C7/12,"还款不足",ROUNDUP(NPER(C7/12,-F7,B7),0))) | I7: =IF(B7<=0,"",IF(G7=1,"优先偿还","维持最低还款"))
B8: 0 | C8: 0 | D8: 0 | E8: 0 | F8: =D8+E8 -> 0 | G8: =IF(B8>0,RANK(C8,$C$4:$C$21,0),"") | H8: =IF(B8<=0,"",IF(F8<=B8*C8/12,"还款不足",ROUNDUP(NPER(C8/12,-F8,B8),0))) | I8: =IF(B8<=0,"",IF(G8=1,"优先偿还","维持最低还款"))
B9: 0 | C9: 0 | D9: 0 | E9: 0 | F9: =D9+E9 -> 0 | G9: =IF(B9>0,RANK(C9,$C$4:$C$21,0),"") | H9: =IF(B9<=0,"",IF(F9<=B9*C9/12,"还款不足",ROUNDUP(NPER(C9/12,-F9,B9),0))) | I9: =IF(B9<=0,"",IF(G9=1,"优先偿还","维持最低还款"))
B10: 0 | C10: 0 | D10: 0 | E10: 0 | F10: =D10+E10 -> 0 | G10: =IF(B10>0,RANK(C10,$C$4:$C$21,0),"") | H10: =IF(B10<=0,"",IF(F10<=B10*C10/12,"还款不足",ROUNDUP(NPER(C10/12,-F10,B10),0))) | I10: =IF(B10<=0,"",IF(G10=1,"优先偿还","维持最低还款"))
B11: 0 | C11: 0 | D11: 0 | E11: 0 | F11: =D11+E11 -> 0 | G11: =IF(B11>0,RANK(C11,$C$4:$C$21,0),"") | H11: =IF(B11<=0,"",IF(F11<=B11*C11/12,"还款不足",ROUNDUP(NPER(C11/12,-F11,B11),0))) | I11: =IF(B11<=0,"",IF(G11=1,"优先偿还","维持最低还款"))
B12: 0 | C12: 0 | D12: 0 | E12: 0 | F12: =D12+E12 -> 0 | G12: =IF(B12>0,RANK(C12,$C$4:$C$21,0),"") | H12: =IF(B12<=0,"",IF(F12<=B12*C12/12,"还款不足",ROUNDUP(NPER(C12/12,-F12,B12),0))) | I12: =IF(B12<=0,"",IF(G12=1,"优先偿还","维持最低还款"))
B13: 0 | C13: 0 | D13: 0 | E13: 0 | F13: =D13+E13 -> 0 | G13: =IF(B13>0,RANK(C13,$C$4:$C$21,0),"") | H13: =IF(B13<=0,"",IF(F13<=B13*C13/12,"还款不足",ROUNDUP(NPER(C13/12,-F13,B13),0))) | I13: =IF(B13<=0,"",IF(G13=1,"优先偿还","维持最低还款"))
B14: 0 | C14: 0 | D14: 0 | E14: 0 | F14: =D14+E14 -> 0 | G14: =IF(B14>0,RANK(C14,$C$4:$C$21,0),"") | H14: =IF(B14<=0,"",IF(F14<=B14*C14/12,"还款不足",ROUNDUP(NPER(C14/12,-F14,B14),0))) | I14: =IF(B14<=0,"",IF(G14=1,"优先偿还","维持最低还款"))
B15: 0 | C15: 0 | D15: 0 | E15: 0 | F15: =D15+E15 -> 0 | G15: =IF(B15>0,RANK(C15,$C$4:$C$21,0),"") | H15: =IF(B15<=0,"",IF(F15<=B15*C15/12,"还款不足",ROUNDUP(NPER(C15/12,-F15,B15),0))) | I15: =IF(B15<=0,"",IF(G15=1,"优先偿还","维持最低还款"))
B16: 0 | C16: 0 | D16: 0 | E16: 0 | F16: =D16+E16 -> 0 | G16: =IF(B16>0,RANK(C16,$C$4:$C$21,0),"") | H16: =IF(B16<=0,"",IF(F16<=B16*C16/12,"还款不足",ROUNDUP(NPER(C16/12,-F16,B16),0))) | I16: =IF(B16<=0,"",IF(G16=1,"优先偿还","维持最低还款"))
B17: 0 | C17: 0 | D17: 0 | E17: 0 | F17: =D17+E17 -> 0 | G17: =IF(B17>0,RANK(C17,$C$4:$C$21,0),"") | H17: =IF(B17<=0,"",IF(F17<=B17*C17/12,"还款不足",ROUNDUP(NPER(C17/12,-F17,B17),0))) | I17: =IF(B17<=0,"",IF(G17=1,"优先偿还","维持最低还款"))
B18: 0 | C18: 0 | D18: 0 | E18: 0 | F18: =D18+E18 -> 0 | G18: =IF(B18>0,RANK(C18,$C$4:$C$21,0),"") | H18: =IF(B18<=0,"",IF(F18<=B18*C18/12,"还款不足",ROUNDUP(NPER(C18/12,-F18,B18),0))) | I18: =IF(B18<=0,"",IF(G18=1,"优先偿还","维持最低还款"))
... B21: 0 | C21: 0 | D21: 0 | E21: 0 | F21: =D21+E21 -> 0 | G21: =IF(B21>0,RANK(C21,$C$4:$C$21,0),"") | H21: =IF(B21<=0,"",IF(F21<=B21*C21/12,"还款不足",ROUNDUP(NPER(C21/12,-F21,B21),0))) | I21: =IF(B21<=0,"",IF(G21=1,"优先偿还","维持最低还款"))
A23: 汇总
A24: 总债务余额 | B24: =SUM(B4:B21) -> 0 | C24: 本月计划还款 | D24: =SUM(F4:F21) -> 0 | E24: 提示 | F24: 优先把额外收入中的还债部分投向最高利率债务

Sheet 资产配置
A1: 资产配置｜分散风险，定期再平衡
A3: 资产类别 | B3: 当前金额 | C3: 目标比例 | D3: 当前比例 | E3: 偏差 | F3: 建议调整金额 | G3: 备注
A4: 现金/活期 | B4: 3000 | C4: 0.15 | D4: =IFERROR(B4/$B$11,0) -> 0.19736842 | E4: =D4-C4 -> 0.047368421 | F4: =$B$11*C4-B4 -> -720 | G4: 日常流动性
A5: 应急金 | B5: 1200 | C5: 0.2 | D5: =IFERROR(B5/$B$11,0) -> 0.078947368 | E5: =D5-C5 -> -0.12105263 | F5: =$B$11*C5-B5 -> 1840 | G5: 先补足目标
A6: 债券/固收 | B6: 4000 | C6: 0.25 | D6: =IFERROR(B6/$B$11,0) -> 0.26315789 | E6: =D6-C6 -> 0.013157895 | F6: =$B$11*C6-B6 -> -200 | G6: 稳定组合
A7: 权益基金/股票 | B7: 6000 | C7: 0.35 | D7: =IFERROR(B7/$B$11,0) -> 0.39473684 | E7: =D7-C7 -> 0.044736842 | F7: =$B$11*C7-B7 -> -680 | G7: 长期增长
A8: 黄金/商品 | B8: 1000 | C8: 0.05 | D8: =IFERROR(B8/$B$11,0) -> 0.065789474 | E8: =D8-C8 -> 0.015789474 | F8: =$B$11*C8-B8 -> -240 | G8: 小比例分散
A9: 其他 | B9: 0 | C9: 0 | D9: =IFERROR(B9/$B$11,0) -> 0 | E9: =D9-C9 -> 0 | F9: =$B$11*C9-B9 -> 0
A11: 合计 | B11: =SUM(B4:B9) -> 15200 | C11: =SUM(C4:C9) -> 1 | D11: =SUM(D4:D9) -> 1

Sheet 目标计划
A1: 目标计划｜把不定期收入转化为明确目标
A3: 目标名称 | B3: 目标类型 | C3: 目标金额 | D3: 当前金额 | E3: 每月投入 | F3: 目标日期 | G3: 完成率 | H3: 预计还需月数 | I3: 状态
A4: 应急金目标 | B4: 安全垫 | C4: =应急金!$B$7 -> 12000 | D4: =应急金!$B$10 -> 1200 | E4: 1200 | F4: 46387 | G4: =IFERROR(D4/C4,0) -> 0.1 | H4: =IF(OR(C4<=D4,E4<=0),0,ROUNDUP((C4-D4)/E4,0)) -> 9 | I4: =IF(C4<=0,"",IF(G4>=1,"已完成",IF(F4<TODAY(),"已逾期","进行中"))) -> 进行中
A5: 年度旅行/学习准备金 | B5: 专项准备金 | C5: 6000 | D5: 400 | E5: 500 | F5: 46387 | G5: =IFERROR(D5/C5,0) -> 0.066666667 | H5: =IF(OR(C5<=D5,E5<=0),0,ROUNDUP((C5-D5)/E5,0)) -> 12 | I5: =IF(C5<=0,"",IF(G5>=1,"已完成",IF(F5<TODAY(),"已逾期","进行中"))) -> 进行中
A6: 长期投资账户 | B6: 长期投资 | C6: 30000 | D6: 6000 | E6: 1500 | F6: 46752 | G6: =IFERROR(D6/C6,0) -> 0.2 | H6: =IF(OR(C6<=D6,E6<=0),0,ROUNDUP((C6-D6)/E6,0)) -> 16 | I6: =IF(C6<=0,"",IF(G6>=1,"已完成",IF(F6<TODAY(),"已逾期","进行中"))) -> 进行中
C7: 0 | D7: 0 | E7: 0 | G7: =IFERROR(D7/C7,0) -> 0 | H7: =IF(OR(C7<=D7,E7<=0),0,ROUNDUP((C7-D7)/E7,0)) -> 0 | I7: =IF(C7<=0,"",IF(G7>=1,"已完成",IF(F7<TODAY(),"已逾期","进行中")))
C8: 0 | D8: 0 | E8: 0 | G8: =IFERROR(D8/C8,0) -> 0 | H8: =IF(OR(C8<=D8,E8<=0),0,ROUNDUP((C8-D8)/E8,0)) -> 0 | I8: =IF(C8<=0,"",IF(G8>=1,"已完成",IF(F8<TODAY(),"已逾期","进行中")))
C9: 0 | D9: 0 | E9: 0 | G9: =IFERROR(D9/C9,0) -> 0 | H9: =IF(OR(C9<=D9,E9<=0),0,ROUNDUP((C9-D9)/E9,0)) -> 0 | I9: =IF(C9<=0,"",IF(G9>=1,"已完成",IF(F9<TODAY(),"已逾期","进行中")))
C10: 0 | D10: 0 | E10: 0 | G10: =IFERROR(D10/C10,0) -> 0 | H10: =IF(OR(C10<=D10,E10<=0),0,ROUNDUP((C10-D10)/E10,0)) -> 0 | I10: =IF(C10<=0,"",IF(G10>=1,"已完成",IF(F10<TODAY(),"已逾期","进行中")))
C11: 0 | D11: 0 | E11: 0 | G11: =IFERROR(D11/C11,0) -> 0 | H11: =IF(OR(C11<=D11,E11<=0),0,ROUNDUP((C11-D11)/E11,0)) -> 0 | I11: =IF(C11<=0,"",IF(G11>=1,"已完成",IF(F11<TODAY(),"已逾期","进行中")))
C12: 0 | D12: 0 | E12: 0 | G12: =IFERROR(D12/C12,0) -> 0 | H12: =IF(OR(C12<=D12,E12<=0),0,ROUNDUP((C12-D12)/E12,0)) -> 0 | I12: =IF(C12<=0,"",IF(G12>=1,"已完成",IF(F12<TODAY(),"已逾期","进行中")))
C13: 0 | D13: 0 | E13: 0 | G13: =IFERROR(D13/C13,0) -> 0 | H13: =IF(OR(C13<=D13,E13<=0),0,ROUNDUP((C13-D13)/E13,0)) -> 0 | I13: =IF(C13<=0,"",IF(G13>=1,"已完成",IF(F13<TODAY(),"已逾期","进行中")))
C14: 0 | D14: 0 | E14: 0 | G14: =IFERROR(D14/C14,0) -> 0 | H14: =IF(OR(C14<=D14,E14<=0),0,ROUNDUP((C14-D14)/E14,0)) -> 0 | I14: =IF(C14<=0,"",IF(G14>=1,"已完成",IF(F14<TODAY(),"已逾期","进行中")))
C15: 0 | D15: 0 | E15: 0 | G15: =IFERROR(D15/C15,0) -> 0 | H15: =IF(OR(C15<=D15,E15<=0),0,ROUNDUP((C15-D15)/E15,0)) -> 0 | I15: =IF(C15<=0,"",IF(G15>=1,"已完成",IF(F15<TODAY(),"已逾期","进行中")))
C16: 0 | D16: 0 | E16: 0 | G16: =IFERROR(D16/C16,0) -> 0 | H16: =IF(OR(C16<=D16,E16<=0),0,ROUNDUP((C16-D16)/E16,0)) -> 0 | I16: =IF(C16<=0,"",IF(G16>=1,"已完成",IF(F16<TODAY(),"已逾期","进行中")))
C17: 0 | D17: 0 | E17: 0 | G17: =IFERROR(D17/C17,0) -> 0 | H17: =IF(OR(C17<=D17,E17<=0),0,ROUNDUP((C17-D17)/E17,0)) -> 0 | I17: =IF(C17<=0,"",IF(G17>=1,"已完成",IF(F17<TODAY(),"已逾期","进行中")))
C18: 0 | D18: 0 | E18: 0 | G18: =IFERROR(D18/C18,0) -> 0 | H18: =IF(OR(C18<=D18,E18<=0),0,ROUNDUP((C18-D18)/E18,0)) -> 0 | I18: =IF(C18<=0,"",IF(G18>=1,"已完成",IF(F18<TODAY(),"已逾期","进行中")))
... C21: 0 | D21: 0 | E21: 0 | G21: =IFERROR(D21/C21,0) -> 0 | H21: =IF(OR(C21<=D21,E21<=0),0,ROUNDUP((C21-D21)/E21,0)) -> 0 | I21: =IF(C21<=0,"",IF(G21>=1,"已完成",IF(F21<TODAY(),"已逾期","进行中")))

Sheet 资料来源
A1: 资料来源与模型说明
A3: 用途 | B3: 说明 | C3: 来源/链接 | D3: 备注
A4: 预算分配 | B4: 模板使用 50/30/20 思路，并按用户浮动收入情况改成保守基准 + 额外收入分配。 | C4: https://files.consumerfinance.gov/f/documents/cfpb_worksheet_my-spending-rule-to-live-by.pdf | D4: 比例可在《参数设置》修改。
A5: 应急金 | B5: 模板用 3 个月必要生活费作为初始目标，可逐步提高。 | C5: https://www.consumerfinance.gov/an-essential-guide-to-building-an-emergency-fund/ | D5: 目标月数可修改。
A6: 资产配置 | B6: 资产配置应按期限、风险承受能力和现金流调整。 | C6: https://www.investor.gov/introduction-investing/getting-started/asset-allocation | D6: 不构成投资建议。
A7: 个人输入 | B7: 工资下限 7000、工资上限 8500、非工资收入不定期不定额。 | C7: 用户提供 | D7: 模板已按这些条件调整。
